LICENSE.md
pyphysim/.mypy_cache/3.7/@plugins_snapshot.json
pyphysim/.mypy_cache/3.7/_ast.data.json
pyphysim/.mypy_cache/3.7/_ast.meta.json
pyphysim/.mypy_cache/3.7/_importlib_modulespec.data.json
pyphysim/.mypy_cache/3.7/_importlib_modulespec.meta.json
pyphysim/.mypy_cache/3.7/abc.data.json
pyphysim/.mypy_cache/3.7/abc.meta.json
pyphysim/.mypy_cache/3.7/ast.data.json
pyphysim/.mypy_cache/3.7/ast.meta.json
pyphysim/.mypy_cache/3.7/builtins.data.json
pyphysim/.mypy_cache/3.7/builtins.meta.json
pyphysim/.mypy_cache/3.7/codecs.data.json
pyphysim/.mypy_cache/3.7/codecs.meta.json
pyphysim/.mypy_cache/3.7/collections/__init__.data.json
pyphysim/.mypy_cache/3.7/collections/__init__.meta.json
pyphysim/.mypy_cache/3.7/collections/abc.data.json
pyphysim/.mypy_cache/3.7/collections/abc.meta.json
pyphysim/.mypy_cache/3.7/importlib/__init__.data.json
pyphysim/.mypy_cache/3.7/importlib/__init__.meta.json
pyphysim/.mypy_cache/3.7/importlib/abc.data.json
pyphysim/.mypy_cache/3.7/importlib/abc.meta.json
pyphysim/.mypy_cache/3.7/io.data.json
pyphysim/.mypy_cache/3.7/io.meta.json
pyphysim/.mypy_cache/3.7/mmap.data.json
pyphysim/.mypy_cache/3.7/mmap.meta.json
pyphysim/.mypy_cache/3.7/os/__init__.data.json
pyphysim/.mypy_cache/3.7/os/__init__.meta.json
pyphysim/.mypy_cache/3.7/os/path.data.json
pyphysim/.mypy_cache/3.7/os/path.meta.json
pyphysim/.mypy_cache/3.7/posix.data.json
pyphysim/.mypy_cache/3.7/posix.meta.json
pyphysim/.mypy_cache/3.7/sys.data.json
pyphysim/.mypy_cache/3.7/sys.meta.json
pyphysim/.mypy_cache/3.7/types.data.json
pyphysim/.mypy_cache/3.7/types.meta.json
pyphysim/.mypy_cache/3.7/typing.data.json
pyphysim/.mypy_cache/3.7/typing.meta.json
pyphysim/.mypy_cache/3.7/typing_extensions.data.json
pyphysim/.mypy_cache/3.7/typing_extensions.meta.json
pyphysim/.mypy_cache/3.8/@plugins_snapshot.json
pyphysim/.mypy_cache/3.8/_ast.data.json
pyphysim/.mypy_cache/3.8/_ast.meta.json
pyphysim/.mypy_cache/3.8/_importlib_modulespec.data.json
pyphysim-0.7.2.dist-info/LICENSE.md
pyphysim-0.7.2.dist-info/WHEEL
pyphysim-0.7.2.dist-info/METADATA
pyphysim-0.7.2.dist-info/RECORD
