Metadata-Version: 2.1
Name: pyphysim
Version: 0.7.2
Summary: Simulation of digital communication (physical layer) in python
Home-page: https://github.com/darcamo/pyphysim
License: GPL-2.0-or-later
Keywords: physical layer,QAM,PSK,QPSK,BPSK,OFDM,Modulation,Monte Carlo,simulation,MIMO,Tapped Delay Line
Author: Darlan Cavalcante Moreira
Author-email: darcamo@gmail.com
Requires-Python: >=3.7,<4.0
Classifier: Development Status :: 5 - Production/Stable
Classifier: Intended Audience :: Education
Classifier: Intended Audience :: Science/Research
Classifier: Intended Audience :: Telecommunications Industry
Classifier: License :: OSI Approved :: GNU General Public License (GPL)
Classifier: License :: OSI Approved :: GNU General Public License v2 or later (GPLv2+)
Classifier: Programming Language :: Python :: 3
Classifier: Programming Language :: Python :: 3.7
Classifier: Programming Language :: Python :: 3.8
Classifier: Topic :: Scientific/Engineering
Requires-Dist: cloudpickle (>=1.5.0,<2.0.0)
Requires-Dist: configobj
Requires-Dist: ipyparallel (>=6.3.0,<7.0.0)
Requires-Dist: ipython (>=7.16.1,<8.0.0)
Requires-Dist: ipywidgets (>=7.5.1,<8.0.0)
Requires-Dist: matplotlib
Requires-Dist: numba
Requires-Dist: numpy
Requires-Dist: pandas (>=1.0.5,<2.0.0)
Requires-Dist: scipy
Project-URL: Repository, https://github.com/darcamo/pyphysim
